yamcs/pymdb/__init__.py
yamcs/pymdb/alarms.py
yamcs/pymdb/algorithms.py
yamcs/pymdb/ancillary.py
yamcs/pymdb/calibrators.py
yamcs/pymdb/ccsds.py
yamcs/pymdb/checks.py
yamcs/pymdb/commands.py
yamcs/pymdb/containers.py
yamcs/pymdb/csp.py
yamcs/pymdb/datatypes.py
yamcs/pymdb/encodings.py
yamcs/pymdb/exceptions.py
yamcs/pymdb/expressions.py
yamcs/pymdb/parameters.py
yamcs/pymdb/systems.py
yamcs/pymdb/verifiers.py
yamcs/pymdb/xtce.py
yamcs_pymdb-1.2.0.dist-info/licenses/LICENSE
yamcs_pymdb-1.2.0.dist-info/METADATA
yamcs_pymdb-1.2.0.dist-info/WHEEL
yamcs_pymdb-1.2.0.dist-info/top_level.txt
yamcs_pymdb-1.2.0.dist-info/RECORD
